[
  {
    "banner": "",
    "ads": "697807440937298_699021580815884",
    "details": "https://pzywx332zzwertw3ccor-euittp0opqwervxt58.github.io/x-m-a/qp/Maths1.pdf",
    "title": "Mathmatics Question 1"
  },
  {
    "banner": "",
    "ads": "697807440937298_699021667482542",
    "details": "https://pzywx332zzwertw3ccor-euittp0opqwervxt58.github.io/x-m-a/qp/Maths2.pdf",
    "title": "Mathmatics Question 2"
  },
  {
    "banner": "",
    "ads": "697807440937298_699021737482535",
    "details": "https://pzywx332zzwertw3ccor-euittp0opqwervxt58.github.io/x-m-a/qp/Maths3.pdf",
    "title": "Mathmatics Question 3"
  },
  {
    "banner": "",
    "ads": "697807440937298_699021827482526",
    "details": "https://pzywx332zzwertw3ccor-euittp0opqwervxt58.github.io/x-m-a/qp/Maths4.pdf",
    "title": "Mathmatics Question 4"
  },
  {
    "banner": "",
    "ads": "697807440937298_699021937482515",
    "details": "https://pzywx332zzwertw3ccor-euittp0opqwervxt58.github.io/x-m-a/qp/Maths5.pdf",
    "title": "Mathmatics Question 5"
  },
  {
    "banner": "",
    "ads": "697807440937298_699021580815884",
    "details": "https://pzywx332zzwertw3ccor-euittp0opqwervxt58.github.io/x-m-a/qp/Maths6.pdf",
    "title": "Mathmatics Question 6"
  }
]